{
    "michael": [
        {
            "name": "San Francisco 49ers"
        },
        {
            "name": "Kansas City Chiefs"
        },
        {
            "name": "Baltimore Ravens"
        },
        {
            "name": "Miami Dolphins"
        },
        {
            "name": "New York Jets"
        },
        {
            "name": "Seattle Seahawks"
        },
        {
            "name": "Houston Texans"
        },
        {
            "name": "New York Giants"
        },
        {
            "name": "Tampa Bay Buccaneers"
        },
        {
            "name": "Minnesota Vikings"
        },
        {
            "name": "Cleveland Browns"
        },
        {
            "name": "Indianapolis Colts"
        },
        {
            "name": "Denver Broncos"
        },
        {
            "name": "Tennessee Titans"
        },
        {
            "name": "Atlanta Falcons"
        },
        {
            "name": "Carolina Panthers"
        }
    ],
    "zach": [
        {
            "name": "Buffalo Bills"
        },
        {
            "name": "Dallas Cowboys"
        },
        {
            "name": "Philadelphia Eagles"
        },
        {
            "name": "Cincinnati Bengals"
        },
        {
            "name": "Jacksonville Jaguars"
        },
        {
            "name": "Green Bay Packers"
        },
        {
            "name": "Los Angeles Chargers"
        },
        {
            "name": "Detroit Lions"
        },
        {
            "name": "New Orleans Saints"
        },
        {
            "name": "Pittsburgh Steelers"
        },
        {
            "name": "Washington Commanders"
        },
        {
            "name": "Las Vegas Raiders"
        },
        {
            "name": "Chicago Bears"
        },
        {
            "name": "New England Patriots"
        },
        {
            "name": "Arizona Cardinals"
        },
        {
            "name": "Los Angeles Rams"
        }
    ]
}