{
    "AFC": {
        "East": [
            {
                "name": "Buffalo Bills",
                "wins": 12
            },
            {
                "name": "Miami Dolphins",
                "wins": 7
            },
            {
                "name": "New England Patriots",
                "wins": 14
            },
            {
                "name": "New York Jets",
                "wins": 3
            }
        ],
        "North": [
            {
                "name": "Baltimore Ravens",
                "wins": 8
            },
            {
                "name": "Cincinnati Bengals",
                "wins": 6
            },
            {
                "name": "Cleveland Browns",
                "wins": 5
            },
            {
                "name": "Pittsburgh Steelers",
                "wins": 10
            }
        ],
        "South": [
            {
                "name": "Houston Texans",
                "wins": 12
            },
            {
                "name": "Indianapolis Colts",
                "wins": 8
            },
            {
                "name": "Jacksonville Jaguars",
                "wins": 13
            },
            {
                "name": "Tennessee Titans",
                "wins": 3
            }
        ],
        "West": [
            {
                "name": "Denver Broncos",
                "wins": 14
            },
            {
                "name": "Kansas City Chiefs",
                "wins": 6
            },
            {
                "name": "Las Vegas Raiders",
                "wins": 3
            },
            {
                "name": "Los Angeles Chargers",
                "wins": 11
            }
        ]
    },
    "NFC": {
        "East": [
            {
                "name": "Dallas Cowboys",
                "wins": 7
            },
            {
                "name": "New York Giants",
                "wins": 4
            },
            {
                "name": "Philadelphia Eagles",
                "wins": 11
            },
            {
                "name": "Washington Commanders",
                "wins": 5
            }
        ],
        "North": [
            {
                "name": "Chicago Bears",
                "wins": 11
            },
            {
                "name": "Detroit Lions",
                "wins": 9
            },
            {
                "name": "Green Bay Packers",
                "wins": 9
            },
            {
                "name": "Minnesota Vikings",
                "wins": 9
            }
        ],
        "South": [
            {
                "name": "Atlanta Falcons",
                "wins": 8
            },
            {
                "name": "Carolina Panthers",
                "wins": 8
            },
            {
                "name": "New Orleans Saints",
                "wins": 6
            },
            {
                "name": "Tampa Bay Buccaneers",
                "wins": 8
            }
        ],
        "West": [
            {
                "name": "Arizona Cardinals",
                "wins": 3
            },
            {
                "name": "Los Angeles Rams",
                "wins": 12
            },
            {
                "name": "San Francisco 49ers",
                "wins": 12
            },
            {
                "name": "Seattle Seahawks",
                "wins": 14
            }
        ]
    }
}
